cortx_jupyter/__init__.py
cortx_jupyter/constants.py
cortx_jupyter/cortx_authenticator.py
cortx_jupyter/cortx_file_manager.py
cortx_jupyter/cortx_jupyter.py
cortx_jupyter/utils.py
cortx_jupyter-0.1.135.dist-info/LICENSE
cortx_jupyter-0.1.135.dist-info/METADATA
cortx_jupyter-0.1.135.dist-info/WHEEL
cortx_jupyter-0.1.135.dist-info/top_level.txt
cortx_jupyter-0.1.135.dist-info/RECORD
