Metadata-Version: 2.1
Name: cortx-jupyter
Version: 0.1.135
Summary: Jupyter Notebook Manager for Cortx
Home-page: https://github.com/sumanthreddym/cortx_jupyter
Author: Sumanth Reddy Muni & Priyadarshini Murugan
License: UNKNOWN
Platform: UNKNOWN
Requires-Dist: traitlets
Requires-Dist: tornado
Requires-Dist: boto3
Requires-Dist: joblib
Requires-Dist: pandas
Requires-Dist: numpy
Requires-Dist: notebook
Requires-Dist: nbformat
Requires-Dist: asyncio
